dnaplotlib/__init__.py
dnaplotlib/dnaplotlib.py
dnaplotlib/sbol/__init__.py
dnaplotlib/sbol/sbolplotlib.py
dnaplotlib2-1.0.data/scripts/library_plot.py
dnaplotlib2-1.0.data/scripts/quick.py
dnaplotlib2-1.0.dist-info/LICENSE.txt
dnaplotlib2-1.0.dist-info/METADATA
dnaplotlib2-1.0.dist-info/WHEEL
dnaplotlib2-1.0.dist-info/top_level.txt
dnaplotlib2-1.0.dist-info/RECORD
