Metadata-Version: 2.1
Name: dnaplotlib2
Version: 1.0
Summary: Genetic design visualization
Home-page: https://github.com/VoigtLab/dnaplotlib
Download-URL: https://github.com/VoigtLab/dnaplotlib/archive/1.0.tar.gz
Author: Thomas Gorochowski, 
Author-email: Thomas Gorochowski <tom@chofski.co.uk>, MIT iGEM <mit-igem@mit.edu>
Project-URL: Homepage, https://github.com/mit-igem/dnaplotlib
Project-URL: Bug Tracker, https://github.com/mit-igem/dnaplotlib
Keywords: visualization,SBOLv,genetic design,synthetic biology,systems biology
Classifier: Programming Language :: Python :: 3
Classifier: License :: OSI Approved :: MIT License
Classifier: Operating System :: OS Independent
Requires-Python: >=3.7
License-File: LICENSE.txt
